{"date":"2022-08-29","results":[{"title":"Drop-If-Exists","sql":"DROP TABLE IF EXISTS hits ALL;","lines":[30.53,30.53,30.53,30.53],"version":"v0.8.14-nightly","xAxis":["min","max","median","mean"]},{"title":"Create-Table","sql":"CREATE TABLE hits (\n  WatchID BIGINT NOT NULL,\n  JavaEnable SMALLINT NOT NULL,\n  Title VARCHAR NOT NULL,\n  GoodEvent SMALLINT NOT NULL,\n  EventTime TIMESTAMP NOT NULL,\n  EventDate Date NOT NULL,\n  CounterID INTEGER NOT NULL,\n  ClientIP INTEGER NOT NULL,\n  RegionID INTEGER NOT NULL,\n  UserID BIGINT NOT NULL,\n  CounterClass SMALLINT NOT NULL,\n  OS SMALLINT NOT NULL,\n  UserAgent SMALLINT NOT NULL,\n  URL VARCHAR NOT NULL,\n  Referer VARCHAR NOT NULL,\n  IsRefresh SMALLINT NOT NULL,\n  RefererCategoryID SMALLINT NOT NULL,\n  RefererRegionID INTEGER NOT NULL,\n  URLCategoryID SMALLINT NOT NULL,\n  URLRegionID INTEGER NOT NULL,\n  ResolutionWidth SMALLINT NOT NULL,\n  ResolutionHeight SMALLINT NOT NULL,\n  ResolutionDepth SMALLINT NOT NULL,\n  FlashMajor SMALLINT NOT NULL,\n  FlashMinor SMALLINT NOT NULL,\n  FlashMinor2 VARCHAR NOT NULL,\n  NetMajor SMALLINT NOT NULL,\n  NetMinor SMALLINT NOT NULL,\n  UserAgentMajor SMALLINT NOT NULL,\n  UserAgentMinor VARCHAR(255) NOT NULL,\n  CookieEnable SMALLINT NOT NULL,\n  JavascriptEnable SMALLINT NOT NULL,\n  IsMobile SMALLINT NOT NULL,\n  MobilePhone SMALLINT NOT NULL,\n  MobilePhoneModel VARCHAR NOT NULL,\n  Params VARCHAR NOT NULL,\n  IPNetworkID INTEGER NOT NULL,\n  TraficSourceID SMALLINT NOT NULL,\n  SearchEngineID SMALLINT NOT NULL,\n  SearchPhrase VARCHAR NOT NULL,\n  AdvEngineID SMALLINT NOT NULL,\n  IsArtifical SMALLINT NOT NULL,\n  WindowClientWidth SMALLINT NOT NULL,\n  WindowClientHeight SMALLINT NOT NULL,\n  ClientTimeZone SMALLINT NOT NULL,\n  ClientEventTime TIMESTAMP NOT NULL,\n  SilverlightVersion1 SMALLINT NOT NULL,\n  SilverlightVersion2 SMALLINT NOT NULL,\n  SilverlightVersion3 INTEGER NOT NULL,\n  SilverlightVersion4 SMALLINT NOT NULL,\n  PageCharset VARCHAR NOT NULL,\n  CodeVersion INTEGER NOT NULL,\n  IsLink SMALLINT NOT NULL,\n  IsDownload SMALLINT NOT NULL,\n  IsNotBounce SMALLINT NOT NULL,\n  FUniqID BIGINT NOT NULL,\n  OriginalURL VARCHAR NOT NULL,\n  HID INTEGER NOT NULL,\n  IsOldCounter SMALLINT NOT NULL,\n  IsEvent SMALLINT NOT NULL,\n  IsParameter SMALLINT NOT NULL,\n  DontCountHits SMALLINT NOT NULL,\n  WithHash SMALLINT NOT NULL,\n  HitColor VARCHAR NOT NULL,\n  LocalEventTime TIMESTAMP NOT NULL,\n  Age SMALLINT NOT NULL,\n  Sex SMALLINT NOT NULL,\n  Income SMALLINT NOT NULL,\n  Interests SMALLINT NOT NULL,\n  Robotness SMALLINT NOT NULL,\n  RemoteIP INTEGER NOT NULL,\n  WindowName INTEGER NOT NULL,\n  OpenerName INTEGER NOT NULL,\n  HistoryLength SMALLINT NOT NULL,\n  BrowserLanguage VARCHAR NOT NULL,\n  BrowserCountry VARCHAR NOT NULL,\n  SocialNetwork VARCHAR NOT NULL,\n  SocialAction VARCHAR NOT NULL,\n  HTTPError SMALLINT NOT NULL,\n  SendTiming INTEGER NOT NULL,\n  DNSTiming INTEGER NOT NULL,\n  ConnectTiming INTEGER NOT NULL,\n  ResponseStartTiming INTEGER NOT NULL,\n  ResponseEndTiming INTEGER NOT NULL,\n  FetchTiming INTEGER NOT NULL,\n  SocialSourceNetworkID SMALLINT NOT NULL,\n  SocialSourcePage VARCHAR NOT NULL,\n  ParamPrice BIGINT NOT NULL,\n  ParamOrderID VARCHAR NOT NULL,\n  ParamCurrency VARCHAR NOT NULL,\n  ParamCurrencyID SMALLINT NOT NULL,\n  OpenstatServiceName VARCHAR NOT NULL,\n  OpenstatCampaignID VARCHAR NOT NULL,\n  OpenstatAdID VARCHAR NOT NULL,\n  OpenstatSourceID VARCHAR NOT NULL,\n  UTMSource VARCHAR NOT NULL,\n  UTMMedium VARCHAR NOT NULL,\n  UTMCampaign VARCHAR NOT NULL,\n  UTMContent VARCHAR NOT NULL,\n  UTMTerm VARCHAR NOT NULL,\n  FromTag VARCHAR NOT NULL,\n  HasGCLID SMALLINT NOT NULL,\n  RefererHash BIGINT NOT NULL,\n  URLHash BIGINT NOT NULL,\n  CLID INTEGER NOT NULL\n);\n","lines":[0.086,0.086,0.086,0.086],"version":"v0.8.14-nightly","xAxis":["min","max","median","mean"]},{"title":"Reload-hits","sql":"COPY INTO hits FROM 's3://repo.databend.rs/hits_p/' credentials=(aws_key_id='{{ \"AWS_KEY_ID\" | env }}' aws_secret_key='{{ \"AWS_SECRET_KEY\" | env }}') pattern ='.*[.]tsv' file_format=(type='TSV' field_delimiter='\\\\t' record_delimiter='\\\\n' skip_header=1);\n","lines":[412.111,412.111,412.111,412.111],"version":"v0.8.14-nightly","xAxis":["min","max","median","mean"]},{"title":"Select-Count","sql":"SELECT count(*) FROM hits;","lines":[2.092,2.092,2.092,2.092],"version":"v0.8.14-nightly","xAxis":["min","max","median","mean"]}]}