{"metadata":{"table":"hits","tag":"v0.8.144-nightly","size":"Large"},"schema":[{"name":"Q1","sql":"SELECT COUNT(*) FROM hits;","min":0.021,"max":0.029,"median":0.025500000000000002,"std_dev":0.0023,"read_row":1,"read_byte":1,"time":[0.026,0.029,0.026,0.025,0.024,0.023,0.023,0.026,0.021,0.028],"error":[],"mean":0.0249936813744901},{"name":"Q2","sql":"SELECT COUNT(*) FROM hits WHERE AdvEngineID \u003c\u003e 0;","min":1.006,"max":1.269,"median":1.1355,"std_dev":0.08560660021283406,"read_row":86362649,"read_byte":172725298,"time":[1.269,1.134,1.165,1.17,1.034,1.137,1.023,1.006,1.233,1.06],"error":[],"mean":1.1198529602164742},{"name":"Q3","sql":"SELECT SUM(AdvEngineID), COUNT(*), AVG(ResolutionWidth) FROM hits;","min":0.986,"max":1.229,"median":1.0779999999999998,"std_dev":0.05852315780953727,"read_row":99997397,"read_byte":399989588,"time":[1.119,1.071,1.085,1.114,1.07,1.06,1.229,1.103,1.061,0.986],"error":[],"mean":1.0882642994264056},{"name":"Q4","sql":"SELECT AVG(UserID) FROM hits;","min":0.994,"max":7.527,"median":1.12,"std_dev":2.488801832207619,"read_row":99997397,"read_byte":799979176,"time":[1.174,1.073,5.015,1.121,1.063,0.994,7.527,6.591,1.091,1.119],"error":[],"mean":1.8434408550120673},{"name":"Q5","sql":"SELECT COUNT(DISTINCT UserID) FROM hits;","min":4.236,"max":4.401,"median":4.339,"std_dev":0.04700468061799801,"read_row":99997397,"read_byte":799979176,"time":[4.33,4.352,4.34,4.401,4.267,4.333,4.373,4.338,4.374,4.236],"error":[],"mean":4.334143604337815},{"name":"Q6","sql":"SELECT COUNT(DISTINCT SearchPhrase) FROM hits;","min":2.644,"max":2.901,"median":2.7245,"std_dev":0.07210332863328847,"read_row":99997397,"read_byte":1539621310,"time":[2.773,2.698,2.644,2.745,2.739,2.71,2.833,2.901,2.682,2.706],"error":[],"mean":2.7421662458466285},{"name":"Q7","sql":"SELECT MIN(EventDate), MAX(EventDate) FROM hits;","min":0.99,"max":1.075,"median":1.0465,"std_dev":0.025013796193301005,"read_row":99997397,"read_byte":399989588,"time":[1.02,1.071,1.049,1.044,1.036,1.062,0.99,1.075,1.019,1.053],"error":[],"mean":1.0415967390357272},{"name":"Q8","sql":"SELECT AdvEngineID, COUNT(*) FROM hits WHERE AdvEngineID \u003c\u003e 0 GROUP BY AdvEngineID ORDER BY COUNT(*) DESC;","min":1.07,"max":2.215,"median":1.2375,"std_dev":0.3157400829796559,"read_row":86362649,"read_byte":172725298,"time":[1.196,1.353,2.215,1.232,1.489,1.07,1.128,1.136,1.243,1.248],"error":[],"mean":1.3018666551408964},{"name":"Q9","sql":"SELECT RegionID, COUNT(DISTINCT UserID) AS u FROM hits GROUP BY RegionID ORDER BY u DESC LIMIT 10;","min":1.719,"max":3.077,"median":1.876,"std_dev":0.3724339001755882,"read_row":99997397,"read_byte":1199968764,"time":[1.801,1.974,1.719,1.79,1.842,1.857,1.895,3.077,1.999,1.903],"error":[],"mean":1.9584295757862509},{"name":"Q10","sql":"SELECT RegionID, SUM(AdvEngineID), COUNT(*) AS c, AVG(ResolutionWidth), COUNT(DISTINCT UserID) FROM hits GROUP BY RegionID ORDER BY c DESC LIMIT 10;","min":1.852,"max":2.288,"median":2.0460000000000003,"std_dev":0.12247893696468784,"read_row":99997397,"read_byte":1599958352,"time":[1.969,1.909,2.134,2.082,2.288,1.995,2.178,2.056,2.036,1.852],"error":[],"mean":2.046268150587325},{"name":"Q11","sql":"SELECT MobilePhoneModel, COUNT(DISTINCT UserID) AS u FROM hits WHERE MobilePhoneModel \u003c\u003e '' GROUP BY MobilePhoneModel ORDER BY u DESC LIMIT 10;","min":1.763,"max":2.165,"median":1.939,"std_dev":0.139311880326123,"read_row":99997397,"read_byte":1623245016,"time":[1.771,2.043,1.886,1.763,1.945,2.165,2.108,1.933,2.142,1.864],"error":[],"mean":1.9570531794269934},{"name":"Q12","sql":"SELECT MobilePhone, MobilePhoneModel, COUNT(DISTINCT UserID) AS u FROM hits WHERE MobilePhoneModel \u003c\u003e '' GROUP BY MobilePhone, MobilePhoneModel ORDER BY u DESC LIMIT 10;","min":1.715,"max":1.985,"median":1.863,"std_dev":0.07931481265295179,"read_row":99997397,"read_byte":1823239810,"time":[1.863,1.834,1.892,1.919,1.715,1.985,1.915,1.778,1.787],"error":["query has error: \u0026{Code:1067 Message:error reading a body from connection: broken pipe, source: Some(hyper::Error(Body, Error { kind: Io(Kind(BrokenPipe)) })) Kind:}"],"mean":1.8525161456524015},{"name":"Q13","sql":"SELECT SearchPhrase, COUNT(*) AS c FROM hits WHERE SearchPhrase \u003c\u003e '' GROUP BY SearchPhrase ORDER BY c DESC LIMIT 10;","min":1.632,"max":1.948,"median":1.7635,"std_dev":0.09136191766814003,"read_row":99997397,"read_byte":1539621310,"time":[1.763,1.764,1.792,1.835,1.807,1.683,1.948,1.659,1.677,1.632],"error":[],"mean":1.7536607390877121},{"name":"Q14","sql":"SELECT SearchPhrase, COUNT(DISTINCT UserID) AS u FROM hits WHERE SearchPhrase \u003c\u003e '' GROUP BY SearchPhrase ORDER BY u DESC LIMIT 10;","min":2.181,"max":8.962,"median":4.4125,"std_dev":2.9565078454149245,"read_row":99997397,"read_byte":2339600486,"time":[8.751,7.819,6.342,8.463,2.181,2.405,8.962,2.483,2.184,2.296],"error":[],"mean":4.29767569087426},{"name":"Q15","sql":"SELECT SearchEngineID, SearchPhrase, COUNT(*) AS c FROM hits WHERE SearchPhrase \u003c\u003e '' GROUP BY SearchEngineID, SearchPhrase ORDER BY c DESC LIMIT 10;","min":1.964,"max":4.161,"median":2.231,"std_dev":0.6288421185003434,"read_row":99997397,"read_byte":1739616104,"time":[2.095,2.22,2.751,2.067,4.161,2.772,2.242,1.98,1.964,2.361],"error":[],"mean":2.397671758944385},{"name":"Q16","sql":"SELECT UserID, COUNT(*) FROM hits GROUP BY UserID ORDER BY COUNT(*) DESC LIMIT 10;","min":2.77,"max":4.038,"median":3.289,"std_dev":0.39256236447219445,"read_row":99997397,"read_byte":799979176,"time":[3.293,2.985,2.77,3.4,2.985,3.732,3.56,2.795,4.038,3.285],"error":[],"mean":3.261305044005088},{"name":"Q17","sql":"SELECT UserID, SearchPhrase, COUNT(*) FROM hits GROUP BY UserID, SearchPhrase ORDER BY COUNT(*) DESC LIMIT 10;","min":5.785,"max":10.108,"median":8.3445,"std_dev":1.4381429727255908,"read_row":99997397,"read_byte":2339600486,"time":[8.34,8.108,5.96,9.129,5.785,8.82,10.108,8.349,6.291,9.437],"error":[],"mean":7.894733132646949},{"name":"Q18","sql":"SELECT UserID, SearchPhrase, COUNT(*) FROM hits GROUP BY UserID, SearchPhrase LIMIT 10;","min":1.966,"max":4.958,"median":2.129,"std_dev":1.027565277731785,"read_row":99997397,"read_byte":2339600486,"time":[2.153,2.079,2.002,2.077,2.249,1.966,4.958,2.105,2.944,4.357],"error":[],"mean":2.5363291005094593},{"name":"Q19","sql":"SELECT UserID, extract(minute FROM EventTime) AS m, SearchPhrase, COUNT(*) FROM hits GROUP BY UserID, m, SearchPhrase ORDER BY COUNT(*) DESC LIMIT 10;","min":8.409,"max":17.412,"median":10.879999999999999,"std_dev":2.5426353965914967,"read_row":99997397,"read_byte":3139579662,"time":[14.285,10.62,11.14,8.409,13.154,9.519,12.397,10.154,9.888,17.412],"error":[],"mean":11.44509586113037},{"name":"Q20","sql":"SELECT UserID FROM hits WHERE UserID = 435090932899640449;","min":0.652,"max":0.902,"median":0.7024999999999999,"std_dev":0.06977169913367454,"read_row":504658,"read_byte":4037264,"time":[0.715,0.667,0.652,0.902,0.721,0.69,0.725,0.661,0.662,0.746],"error":[],"mean":0.7110181135451386},{"name":"Q21","sql":"SELECT COUNT(*) FROM hits WHERE URL LIKE '%google%';","min":2.612,"max":2.973,"median":2.709,"std_dev":0.10008696218788932,"read_row":99997397,"read_byte":9838815578,"time":[2.973,2.656,2.741,2.823,2.834,2.705,2.681,2.612,2.713,2.702],"error":[],"mean":2.742215071246029},{"name":"Q22","sql":"SELECT SearchPhrase, MIN(URL), COUNT(*) AS c FROM hits WHERE URL LIKE '%google%' AND SearchPhrase \u003c\u003e '' GROUP BY SearchPhrase ORDER BY c DESC LIMIT 10;","min":2.935,"max":5.19,"median":3.019,"std_dev":0.6531476096565003,"read_row":99997397,"read_byte":11378436888,"time":[2.996,2.952,2.99,3.018,2.935,3.132,3.02,5.19,3.093,3.054],"error":[],"mean":3.1885275209812356},{"name":"Q23","sql":"SELECT SearchPhrase, MIN(URL), MIN(Title), COUNT(*) AS c, COUNT(DISTINCT UserID) FROM hits WHERE Title LIKE '%Google%' AND URL NOT LIKE '%.google.%' AND SearchPhrase \u003c\u003e '' GROUP BY SearchPhrase ORDER BY c DESC LIMIT 10;","min":5.109,"max":6.359,"median":5.232,"std_dev":0.36860895268563404,"read_row":99997397,"read_byte":22216664351,"time":[5.717,6.359,5.147,5.187,5.277,5.185,5.109,5.37,5.293,5.124],"error":[],"mean":5.365107758000524},{"name":"Q24","sql":"SELECT * FROM hits WHERE URL LIKE '%google%' ORDER BY EventTime LIMIT 10;","min":7.587,"max":15.12,"median":7.875500000000001,"std_dev":2.2443863860752673,"read_row":99997397,"read_byte":70574403404,"time":[7.709,7.687,7.838,10.521,7.587,15.12,8.284,8.01,7.806,7.913],"error":[],"mean":8.632332101004703},{"name":"Q25","sql":"SELECT SearchPhrase FROM hits WHERE SearchPhrase \u003c\u003e '' ORDER BY EventTime LIMIT 10;","min":1.424,"max":3.348,"median":1.506,"std_dev":0.5543155779878461,"read_row":99997397,"read_byte":2339600486,"time":[3.348,1.543,1.581,1.424,1.524,1.483,1.514,1.49,1.498,1.487],"error":[],"mean":1.629616554520182},{"name":"Q26","sql":"SELECT SearchPhrase FROM hits WHERE SearchPhrase \u003c\u003e '' ORDER BY SearchPhrase LIMIT 10;","min":1.045,"max":6.971,"median":1.13,"std_dev":1.8754975579829474,"read_row":99997397,"read_byte":1539621310,"time":[2.17,1.113,1.147,1.163,4.197,1.07,6.971,1.083,1.045,1.062],"error":[],"mean":1.6156917686931915},{"name":"Q27","sql":"SELECT SearchPhrase FROM hits WHERE SearchPhrase \u003c\u003e '' ORDER BY EventTime, SearchPhrase LIMIT 10;","min":1.529,"max":6.717,"median":1.6145,"std_dev":1.5330261608987628,"read_row":99997397,"read_byte":2339600486,"time":[6.717,2.891,1.545,1.61,1.573,1.541,1.739,1.943,1.619,1.529],"error":[],"mean":1.9911023630608822},{"name":"Q28","sql":"SELECT CounterID, AVG(length(URL)) AS l, COUNT(*) AS c FROM hits WHERE URL \u003c\u003e '' GROUP BY CounterID HAVING COUNT(*) \u003e 100000 ORDER BY l DESC LIMIT 25;","min":2.237,"max":8.401,"median":2.3810000000000002,"std_dev":2.0860909951389943,"read_row":99997397,"read_byte":10238805166,"time":[6.337,2.35,2.464,2.344,2.349,2.362,2.4,2.237,5.07,8.401],"error":[],"mean":3.1900162547551885},{"name":"Q30","sql":"SELECT SUM(ResolutionWidth), SUM(ResolutionWidth + 1), SUM(ResolutionWidth + 2), SUM(ResolutionWidth + 3), SUM(ResolutionWidth + 4), SUM(ResolutionWidth + 5), SUM(ResolutionWidth + 6), SUM(ResolutionWidth + 7), SUM(ResolutionWidth + 8), SUM(ResolutionWidth + 9), SUM(ResolutionWidth + 10), SUM(ResolutionWidth + 11), SUM(ResolutionWidth + 12), SUM(ResolutionWidth + 13), SUM(ResolutionWidth + 14), SUM(ResolutionWidth + 15), SUM(ResolutionWidth + 16), SUM(ResolutionWidth + 17), SUM(ResolutionWidth + 18), SUM(ResolutionWidth + 19), SUM(ResolutionWidth + 20), SUM(ResolutionWidth + 21), SUM(ResolutionWidth + 22), SUM(ResolutionWidth + 23), SUM(ResolutionWidth + 24), SUM(ResolutionWidth + 25), SUM(ResolutionWidth + 26), SUM(ResolutionWidth + 27), SUM(ResolutionWidth + 28), SUM(ResolutionWidth + 29), SUM(ResolutionWidth + 30), SUM(ResolutionWidth + 31), SUM(ResolutionWidth + 32), SUM(ResolutionWidth + 33), SUM(ResolutionWidth + 34), SUM(ResolutionWidth + 35), SUM(ResolutionWidth + 36), SUM(ResolutionWidth + 37), SUM(ResolutionWidth + 38), SUM(ResolutionWidth + 39), SUM(ResolutionWidth + 40), SUM(ResolutionWidth + 41), SUM(ResolutionWidth + 42), SUM(ResolutionWidth + 43), SUM(ResolutionWidth + 44), SUM(ResolutionWidth + 45), SUM(ResolutionWidth + 46), SUM(ResolutionWidth + 47), SUM(ResolutionWidth + 48), SUM(ResolutionWidth + 49), SUM(ResolutionWidth + 50), SUM(ResolutionWidth + 51), SUM(ResolutionWidth + 52), SUM(ResolutionWidth + 53), SUM(ResolutionWidth + 54), SUM(ResolutionWidth + 55), SUM(ResolutionWidth + 56), SUM(ResolutionWidth + 57), SUM(ResolutionWidth + 58), SUM(ResolutionWidth + 59), SUM(ResolutionWidth + 60), SUM(ResolutionWidth + 61), SUM(ResolutionWidth + 62), SUM(ResolutionWidth + 63), SUM(ResolutionWidth + 64), SUM(ResolutionWidth + 65), SUM(ResolutionWidth + 66), SUM(ResolutionWidth + 67), SUM(ResolutionWidth + 68), SUM(ResolutionWidth + 69), SUM(ResolutionWidth + 70), SUM(ResolutionWidth + 71), SUM(ResolutionWidth + 72), SUM(ResolutionWidth + 73), SUM(ResolutionWidth + 74), SUM(ResolutionWidth + 75), SUM(ResolutionWidth + 76), SUM(ResolutionWidth + 77), SUM(ResolutionWidth + 78), SUM(ResolutionWidth + 79), SUM(ResolutionWidth + 80), SUM(ResolutionWidth + 81), SUM(ResolutionWidth + 82), SUM(ResolutionWidth + 83), SUM(ResolutionWidth + 84), SUM(ResolutionWidth + 85), SUM(ResolutionWidth + 86), SUM(ResolutionWidth + 87), SUM(ResolutionWidth + 88), SUM(ResolutionWidth + 89) FROM hits;","min":1.241,"max":1.333,"median":1.302,"std_dev":0.029370733732748303,"read_row":99997397,"read_byte":199994794,"time":[1.302,1.241,1.271,1.302,1.333,1.323,1.301,1.325,1.266,1.33],"error":[],"mean":1.2990646996534623},{"name":"Q31","sql":"SELECT SearchEngineID, ClientIP, COUNT(*) AS c, SUM(IsRefresh), AVG(ResolutionWidth) FROM hits WHERE SearchPhrase \u003c\u003e '' GROUP BY SearchEngineID, ClientIP ORDER BY c DESC LIMIT 10;","min":2.631,"max":9.106,"median":2.942,"std_dev":2.4268914870673552,"read_row":99997397,"read_byte":2539595280,"time":[2.884,9.106,8.808,3.115,2.87,2.982,3.007,2.631,2.902,2.806],"error":[],"mean":3.6300174652600794},{"name":"Q32","sql":"SELECT WatchID, ClientIP, COUNT(*) AS c, SUM(IsRefresh), AVG(ResolutionWidth) FROM hits WHERE SearchPhrase \u003c\u003e '' GROUP BY WatchID, ClientIP ORDER BY c DESC LIMIT 10;","min":3.235,"max":10.963,"median":4.640000000000001,"std_dev":2.1774887278697905,"read_row":99997397,"read_byte":3139579662,"time":[4.43,10.963,6.459,4.623,4.736,4.657,3.341,6.267,3.235,3.547],"error":[],"mean":4.881588749363397},{"name":"Q33","sql":"SELECT WatchID, ClientIP, COUNT(*) AS c, SUM(IsRefresh), AVG(ResolutionWidth) FROM hits GROUP BY WatchID, ClientIP ORDER BY c DESC LIMIT 10;","min":16.246,"max":53.236,"median":29.2555,"std_dev":11.197702976950229,"read_row":99997397,"read_byte":1599958352,"time":[46.201,24.334,35.326,25.924,21.524,34.295,20.109,53.236,16.246,32.587],"error":[],"mean":29.068337017235336},{"name":"Q34","sql":"SELECT URL, COUNT(*) AS c FROM hits GROUP BY URL ORDER BY c DESC LIMIT 10;","min":3.941,"max":7.121,"median":4.499,"std_dev":1.112862275595882,"read_row":99997397,"read_byte":9838815578,"time":[6.616,4.107,7.121,4.335,4.667,4.499,4.338,5.955,3.941],"error":["query has error: \u0026{Code:1067 Message:error reading a body from connection: broken pipe, source: Some(hyper::Error(Body, Error { kind: Io(Kind(BrokenPipe)) })) Kind:}"],"mean":4.952704598529975},{"name":"Q35","sql":"SELECT 1, URL, COUNT(*) AS c FROM hits GROUP BY 1, URL ORDER BY c DESC LIMIT 10;","min":15.731,"max":30.169,"median":18.119999999999997,"std_dev":4.472607965158583,"read_row":99997397,"read_byte":9838815578,"time":[22.789,30.169,17.953,17.698,18.282,26.452,17.958,21.142,16.373,15.731],"error":[],"mean":20.017591633494128},{"name":"Q36","sql":"SELECT ClientIP, ClientIP - 1, ClientIP - 2, ClientIP - 3, COUNT(*) AS c FROM hits GROUP BY ClientIP, ClientIP - 1, ClientIP - 2, ClientIP - 3 ORDER BY c DESC LIMIT 10;","min":2.534,"max":5.558,"median":2.717,"std_dev":0.8608596865924202,"read_row":99997397,"read_byte":399989588,"time":[2.991,5.558,2.556,2.534,2.599,2.69,2.951,2.714,3.257,2.72],"error":[],"mean":2.9700425350065838},{"name":"Q37","sql":"SELECT URL, COUNT(*) AS PageViews FROM hits WHERE CounterID = 62 AND EventDate \u003e= '2013-07-01' AND EventDate \u003c= '2013-07-31' AND DontCountHits = 0 AND IsRefresh = 0 AND URL \u003c\u003e '' GROUP BY URL ORDER BY PageViews DESC LIMIT 10;","min":1.064,"max":1.259,"median":1.1865,"std_dev":0.05580143367333852,"read_row":4116673,"read_byte":444042995,"time":[1.221,1.2,1.234,1.064,1.259,1.173,1.117,1.151,1.152,1.209],"error":[],"mean":1.1766531767337909},{"name":"Q38","sql":"SELECT Title, COUNT(*) AS PageViews FROM hits WHERE CounterID = 62 AND EventDate \u003e= '2013-07-01' AND EventDate \u003c= '2013-07-31' AND DontCountHits = 0 AND IsRefresh = 0 AND Title \u003c\u003e '' GROUP BY Title ORDER BY PageViews DESC LIMIT 10;","min":0.926,"max":1.089,"median":1.0270000000000001,"std_dev":0.05564970799564,"read_row":4116673,"read_byte":510363145,"time":[1.032,1.022,1.064,1.061,1.089,1.089,0.973,0.957,0.968,0.926],"error":[],"mean":1.0165656920185464},{"name":"Q39","sql":"SELECT URL, COUNT(*) AS PageViews FROM hits WHERE CounterID = 62 AND EventDate \u003e= '2013-07-01' AND EventDate \u003c= '2013-07-31' AND IsRefresh = 0 AND IsLink \u003c\u003e 0 AND IsDownload = 0 GROUP BY URL ORDER BY PageViews DESC LIMIT 10 OFFSET 1000;","min":0.929,"max":1.163,"median":1.07,"std_dev":0.07633275836755805,"read_row":4116673,"read_byte":452276341,"time":[1.078,1.12,1.124,1.112,0.929,0.944,1.163,1.057,1.062,0.98],"error":[],"mean":1.05407154234317},{"name":"Q40","sql":"SELECT TraficSourceID, SearchEngineID, AdvEngineID, CASE WHEN (SearchEngineID = 0 AND AdvEngineID = 0) THEN Referer ELSE '' END AS Src, URL AS Dst, COUNT(*) AS PageViews FROM hits WHERE CounterID = 62 AND EventDate \u003e= '2013-07-01' AND EventDate \u003c= '2013-07-31' AND IsRefresh = 0 GROUP BY TraficSourceID, SearchEngineID, AdvEngineID, Src, Dst ORDER BY PageViews DESC LIMIT 10 OFFSET 1000;","min":1.515,"max":2.041,"median":1.6745,"std_dev":0.1399434171370701,"read_row":4116673,"read_byte":846664032,"time":[1.515,1.842,1.609,1.62,1.786,2.041,1.645,1.711,1.67,1.679],"error":[],"mean":1.7063498773234904},{"name":"Q41","sql":"SELECT URLHash, EventDate, COUNT(*) AS PageViews FROM hits WHERE CounterID = 62 AND EventDate \u003e= '2013-07-01' AND EventDate \u003c= '2013-07-31' AND IsRefresh = 0 AND TraficSourceID IN (-1, 6) AND RefererHash = 3594120000172545465 GROUP BY URLHash, EventDate ORDER BY PageViews DESC LIMIT 10 OFFSET 100;","min":0.898,"max":1.179,"median":1.038,"std_dev":0.0838642355238513,"read_row":4116673,"read_byte":115266844,"time":[1.12,1.179,1.05,0.967,1.059,1.05,0.898,0.905,0.989,1.026],"error":[],"mean":1.0208692978936522},{"name":"Q42","sql":"SELECT WindowClientWidth, WindowClientHeight, COUNT(*) AS PageViews FROM hits WHERE CounterID = 62 AND EventDate \u003e= '2013-07-01' AND EventDate \u003c= '2013-07-31' AND IsRefresh = 0 AND DontCountHits = 0 AND URLHash = 2868770270353813622 GROUP BY WindowClientWidth, WindowClientHeight ORDER BY PageViews DESC LIMIT 10 OFFSET 10000;","min":0.955,"max":1.249,"median":1.0255,"std_dev":0.085678527064837,"read_row":4116673,"read_byte":98800152,"time":[1.049,1.122,1.249,1.087,0.986,0.975,1.066,0.955,1.002,0.972],"error":[],"mean":1.0429743840917018},{"name":"Q43","sql":"SELECT DATE_TRUNC('minute', EventTime) AS M, COUNT(*) AS PageViews FROM hits WHERE CounterID = 62 AND EventDate \u003e= '2013-07-14' AND EventDate \u003c= '2013-07-15' AND IsRefresh = 0 AND DontCountHits = 0 GROUP BY DATE_TRUNC('minute', EventTime) ORDER BY DATE_TRUNC('minute', EventTime) LIMIT 10 OFFSET 1000;","min":0.903,"max":1.187,"median":1.025,"std_dev":0.08491313208214617,"read_row":4116673,"read_byte":82333460,"time":[0.925,1.014,1.16,0.903,1.038,0.99,0.999,1.036,1.052,1.187],"error":[],"mean":1.0269634041360916}]}