{"metadata":{"table":"ontime","tag":"v0.7.137-nightly","size":"Large"},"schema":[{"name":"Q1","sql":"SELECT DayOfWeek, count(*) AS c FROM default.ontime WHERE Year \u003e= 2000 AND Year \u003c= 2008 GROUP BY DayOfWeek ORDER BY c DESC;","min":0.423,"max":0.525,"median":0.441,"std_dev":0.027833253492899467,"read_row":60000000,"read_byte":180000000,"time":[0.469,0.43,0.436,0.443,0.451,0.525,0.459,0.439,0.436,0.423],"error":[],"mean":0.4502950181370266},{"name":"Q2","sql":"SELECT DayOfWeek, count(*) AS c FROM default.ontime WHERE DepDelay\u003e10 AND Year \u003e= 2000 AND Year \u003c= 2008 GROUP BY DayOfWeek ORDER BY c DESC;","min":0.493,"max":0.683,"median":0.5675,"std_dev":0.06139291490066261,"read_row":60000000,"read_byte":420000000,"time":[0.559,0.683,0.576,0.552,0.493,0.629,0.614,0.497,0.655,0.533],"error":[],"mean":0.5758620920174576},{"name":"Q3","sql":"SELECT Origin, count(*) AS c FROM default.ontime WHERE DepDelay\u003e10 AND Year \u003e= 2000 AND Year \u003c= 2008 GROUP BY Origin ORDER BY c DESC LIMIT 10;","min":0.549,"max":0.999,"median":0.6085,"std_dev":0.1249641548605039,"read_row":60000000,"read_byte":1020000480,"time":[0.592,0.622,0.549,0.556,0.622,0.64,0.595,0.999,0.635,0.556],"error":[],"mean":0.6269978558821407},{"name":"Q4","sql":"SELECT IATA_CODE_Reporting_Airline AS Carrier, count() FROM default.ontime WHERE DepDelay\u003e10 AND Year = 2007 GROUP BY Carrier ORDER BY count() DESC;","min":0.492,"max":0.74,"median":0.616,"std_dev":0.124,"read_row":23000000,"read_byte":368000184,"time":[0.74,0.492],"error":["query has error: \u0026{Code:1002 Message:status: Cancelled, message: \"Timeout expired\", details: [], metadata: MetadataMap { headers: {} } Kind:}","query has error: \u0026{Code:1002 Message:status: Cancelled, message: \"Timeout expired\", details: [], metadata: MetadataMap { headers: {} } Kind:}","query has error: \u0026{Code:1002 Message:status: Cancelled, message: \"Timeout expired\", details: [], metadata: MetadataMap { headers: {} } Kind:}","query has error: \u0026{Code:1002 Message:status: Cancelled, message: \"Timeout expired\", details: [], metadata: MetadataMap { headers: {} } Kind:}","query has error: \u0026{Code:1002 Message:status: Cancelled, message: \"Timeout expired\", details: [], metadata: MetadataMap { headers: {} } Kind:}","query has error: \u0026{Code:1002 Message:status: Cancelled, message: \"Timeout expired\", details: [], metadata: MetadataMap { headers: {} } Kind:}","query has error: \u0026{Code:1002 Message:status: Cancelled, message: \"Timeout expired\", details: [], metadata: MetadataMap { headers: {} } Kind:}","query has error: \u0026{Code:1002 Message:status: Cancelled, message: \"Timeout expired\", details: [], metadata: MetadataMap { headers: {} } Kind:}"],"mean":0.6033904208719261},{"name":"Q5","sql":"SELECT IATA_CODE_Reporting_Airline AS Carrier, avg(cast(DepDelay\u003e10 as Int8))*1000 AS c3 FROM default.ontime WHERE Year=2007 GROUP BY Carrier ORDER BY c3 DESC;","min":0.393,"max":0.466,"median":0.422,"std_dev":0.023647410006171928,"read_row":23000000,"read_byte":368000184,"time":[0.393,0.457,0.404,0.398,0.414,0.466,0.43,0.407,0.433,0.438],"error":[],"mean":0.42334889614113475},{"name":"Q6","sql":"SELECT IATA_CODE_Reporting_Airline AS Carrier, avg(cast(DepDelay\u003e10 as Int8))*1000 AS c3 FROM default.ontime WHERE Year\u003e=2000 AND Year \u003c=2008 GROUP BY Carrier ORDER BY c3 DESC;","min":0.521,"max":0.608,"median":0.557,"std_dev":0.028944947745677456,"read_row":59000000,"read_byte":944000472,"time":[0.594,0.589,0.527,0.521,0.534,0.544,0.552,0.608,0.582,0.562],"error":[],"mean":0.560556275896735},{"name":"Q7","sql":"SELECT IATA_CODE_Reporting_Airline AS Carrier, avg(DepDelay) * 1000 AS c3 FROM default.ontime WHERE Year \u003e= 2000 AND Year \u003c= 2008 GROUP BY Carrier;","min":0.737,"max":0.905,"median":0.7795000000000001,"std_dev":0.050602766722779094,"read_row":59000000,"read_byte":944000472,"time":[0.781,0.905,0.869,0.769,0.776,0.819,0.77,0.737,0.778,0.85],"error":[],"mean":0.8038496163190354},{"name":"Q8","sql":"SELECT Year, avg(DepDelay) FROM default.ontime GROUP BY Year;","min":0.75,"max":0.875,"median":0.81,"std_dev":0.03807164299055137,"read_row":173687555,"read_byte":1042125330,"time":[0.816,0.76,0.875,0.835,0.75,0.808,0.812,0.759,0.821,0.769],"error":[],"mean":0.7996019058294678},{"name":"Q9","sql":"SELECT Year, count(*) as c1 FROM default.ontime GROUP BY Year;","min":0.627,"max":0.839,"median":0.6625000000000001,"std_dev":0.06465013534401919,"read_row":173687555,"read_byte":347375110,"time":[0.653,0.686,0.664,0.627,0.686,0.648,0.839,0.782,0.64,0.661],"error":[],"mean":0.6857916904942604},{"name":"Q10","sql":"SELECT avg(cnt) FROM (SELECT Year,Month,count(*) AS cnt FROM default.ontime WHERE DepDel15=1 GROUP BY Year,Month) a;","min":0.528,"max":0.801,"median":0.5834999999999999,"std_dev":0.08415277773193229,"read_row":173687555,"read_byte":1215812885,"time":[0.536,0.528,0.601,0.566,0.552,0.693,0.801,0.7,0.609,0.565],"error":[],"mean":0.6097556349081178},{"name":"Q11","sql":"SELECT avg(c1) FROM (SELECT Year,Month,count(*) AS c1 FROM default.ontime GROUP BY Year,Month) a;","min":0.515,"max":0.576,"median":0.538,"std_dev":0.01873739576355262,"read_row":173687555,"read_byte":521062665,"time":[0.528,0.52,0.548,0.517,0.553,0.576,0.515,0.534,0.556,0.542],"error":[],"mean":0.5385770642340546},{"name":"Q12","sql":"SELECT OriginCityName, DestCityName, count(*) AS c FROM default.ontime GROUP BY OriginCityName, DestCityName ORDER BY c DESC LIMIT 10;","min":1.509,"max":1.625,"median":1.549,"std_dev":0.030303300150313683,"read_row":173687555,"read_byte":7355842539,"time":[1.543,1.509,1.568,1.578,1.558,1.625,1.554,1.526,1.544,1.536],"error":[],"mean":1.5538078461726375},{"name":"Q13","sql":"SELECT OriginCityName, count(*) AS c FROM default.ontime GROUP BY OriginCityName ORDER BY c DESC LIMIT 10;","min":0.784,"max":0.849,"median":0.8075000000000001,"std_dev":0.01881595068020744,"read_row":173687555,"read_byte":3677948836,"time":[0.804,0.849,0.832,0.8,0.811,0.827,0.784,0.801,0.798,0.828],"error":[],"mean":0.813183433237968},{"name":"Q14","sql":"SELECT count(*) FROM default.ontime;","min":0.039,"max":0.121,"median":0.0445,"std_dev":0.023878023368779918,"read_row":1,"read_byte":1,"time":[0.044,0.061,0.121,0.043,0.039,0.043,0.039,0.045,0.047,0.07],"error":[],"mean":0.05165403373950369}]}