{"metadata":{"table":"ontime","tag":"","size":"XLarge"},"schema":[{"name":"Q1","sql":"SELECT DayOfWeek, count(*) AS c FROM default.ontime WHERE Year \u003e= 2000 AND Year \u003c= 2008 GROUP BY DayOfWeek ORDER BY c DESC;","min":0.106,"max":0.243,"median":0.108,"std_dev":0.0404748069791568,"read_row":0,"read_byte":0,"time":[0.107,0.108,0.109,0.107,0.243,0.107,0.106,0.113,0.109,0.108],"error":[],"mean":0.11732329248141797},{"name":"Q2","sql":"SELECT DayOfWeek, count(*) AS c FROM default.ontime WHERE DepDelay\u003e10 AND Year \u003e= 2000 AND Year \u003c= 2008 GROUP BY DayOfWeek ORDER BY c DESC;","min":0.108,"max":0.116,"median":0.111,"std_dev":0.002418677324489567,"read_row":0,"read_byte":0,"time":[0.111,0.116,0.109,0.112,0.108,0.115,0.11,0.113,0.111,0.11],"error":[],"mean":0.11147394932971692},{"name":"Q3","sql":"SELECT Origin, count(*) AS c FROM default.ontime WHERE DepDelay\u003e10 AND Year \u003e= 2000 AND Year \u003c= 2008 GROUP BY Origin ORDER BY c DESC LIMIT 10;","min":0.107,"max":0.117,"median":0.1115,"std_dev":0.0029051678092667926,"read_row":0,"read_byte":0,"time":[0.107,0.117,0.108,0.111,0.114,0.114,0.109,0.112,0.111,0.113],"error":[],"mean":0.11156223390472828},{"name":"Q4","sql":"SELECT IATA_CODE_Reporting_Airline AS Carrier, count() FROM default.ontime WHERE DepDelay\u003e10 AND Year = 2007 GROUP BY Carrier ORDER BY count() DESC;","min":0.108,"max":0.138,"median":0.111,"std_dev":0.00840297566341829,"read_row":0,"read_byte":0,"time":[0.112,0.138,0.108,0.111,0.11,0.114,0.111,0.111,0.108,0.11],"error":[],"mean":0.1130213206758025},{"name":"Q5","sql":"SELECT IATA_CODE_Reporting_Airline AS Carrier, avg(cast(DepDelay\u003e10 as Int8))*1000 AS c3 FROM default.ontime WHERE Year=2007 GROUP BY Carrier ORDER BY c3 DESC","min":0.108,"max":0.12,"median":0.112,"std_dev":0.003072458299147442,"read_row":0,"read_byte":0,"time":[0.108,0.111,0.11,0.112,0.113,0.115,0.12,0.111,0.112,0.112],"error":[],"mean":0.11235887951710269},{"name":"Q5-JOIN","sql":"SELECT Carrier, c, c2, c*100/c2 as c3 FROM( SELECT IATA_CODE_Reporting_Airline AS Carrier, count(*) AS c FROM ontime WHERE DepDelay\u003e10 AND Year=2007 GROUP BY Carrier) q JOIN ( SELECT IATA_CODE_Reporting_Airline AS Carrier, count(*) AS c2 FROM ontime WHERE Year=2007 GROUP BY Carrier ) qq USING (Carrier) ORDER BY c3 DESC;","min":0.181,"max":0.188,"median":0.1845,"std_dev":0.002374868417407586,"read_row":0,"read_byte":0,"time":[0.182,0.187,0.181,0.188,0.185,0.184,0.181,0.187,0.185,0.184],"error":[],"mean":0.1843846954406291},{"name":"Q6","sql":"SELECT IATA_CODE_Reporting_Airline AS Carrier, avg(cast(DepDelay\u003e10 as Int8))*1000 AS c3 FROM default.ontime WHERE Year\u003e=2000 AND Year \u003c=2008 GROUP BY Carrier ORDER BY c3 DESC;","min":0.107,"max":0.118,"median":0.112,"std_dev":0.003091924966748061,"read_row":0,"read_byte":0,"time":[0.115,0.115,0.109,0.118,0.111,0.113,0.113,0.111,0.11,0.107],"error":[],"mean":0.11215750750568551},{"name":"Q6-JOIN","sql":"SELECT Carrier, c, c2, c*100/c2 as c3 FROM( SELECT IATA_CODE_Reporting_Airline AS Carrier, count(*) AS c FROM ontime WHERE DepDelay\u003e10 AND Year\u003e=2000 AND Year\u003c=2008 GROUP BY Carrier) q JOIN ( SELECT IATA_CODE_Reporting_Airline AS Carrier, count(*) AS c2 FROM ontime WHERE Year\u003e=2000 AND Year\u003c=2008 GROUP BY Carrier ) qq USING (Carrier) ORDER BY c3 DESC;","min":0.178,"max":0.196,"median":0.191,"std_dev":0.005004997502496884,"read_row":0,"read_byte":0,"time":[0.178,0.186,0.191,0.195,0.191,0.191,0.193,0.188,0.196,0.186],"error":[],"mean":0.1894328020690113},{"name":"Q7","sql":"SELECT IATA_CODE_Reporting_Airline AS Carrier, avg(DepDelay) * 1000 AS c3 FROM default.ontime WHERE Year \u003e= 2000 AND Year \u003c= 2008 GROUP BY Carrier;","min":0.105,"max":0.117,"median":0.111,"std_dev":0.003226453160980339,"read_row":0,"read_byte":0,"time":[0.117,0.109,0.112,0.111,0.11,0.112,0.116,0.11,0.111,0.105],"error":[],"mean":0.11125324882141174},{"name":"Q7-JOIN","sql":"SELECT Year, c1/c2 FROM( select Year, count(*)*100 as c1 from ontime WHERE DepDelay\u003e10 GROUP BY Year) q JOIN ( select Year, count(*) as c2 from ontime GROUP BY Year ) qq USING (Year) ORDER BY Year;","min":0.182,"max":0.266,"median":0.1875,"std_dev":0.031060585957125804,"read_row":0,"read_byte":0,"time":[0.266,0.187,0.191,0.184,0.182,0.187,0.262,0.192,0.183,0.188],"error":[],"mean":0.20011050534139888},{"name":"Q8","sql":"SELECT Year, avg(DepDelay) FROM default.ontime GROUP BY Year;","min":0.108,"max":0.114,"median":0.1115,"std_dev":0.001720465053408527,"read_row":0,"read_byte":0,"time":[0.113,0.112,0.108,0.111,0.112,0.114,0.111,0.11,0.109,0.112],"error":[],"mean":0.11118664502146912},{"name":"Q9","sql":"SELECT Year, count(*) as c1 FROM default.ontime GROUP BY Year;","min":0.107,"max":0.113,"median":0.108,"std_dev":0.0024919871588754243,"read_row":0,"read_byte":0,"time":[0.113,0.109,0.108,0.113,0.108,0.108,0.107,0.107,0.113,0.107],"error":[],"mean":0.10927188697039801},{"name":"Q11","sql":"SELECT avg(c1) FROM (SELECT Year,Month,count(*) AS c1 FROM default.ontime GROUP BY Year,Month) a;","min":0.115,"max":0.137,"median":0.1175,"std_dev":0.006053924347066125,"read_row":0,"read_byte":0,"time":[0.115,0.117,0.117,0.12,0.12,0.137,0.118,0.119,0.116,0.116],"error":[],"mean":0.11935751190211619},{"name":"Q12","sql":"SELECT OriginCityName, DestCityName, count(*) AS c FROM default.ontime GROUP BY OriginCityName, DestCityName ORDER BY c DESC LIMIT 10;","min":0.106,"max":0.113,"median":0.1105,"std_dev":0.002118962010041711,"read_row":0,"read_byte":0,"time":[0.107,0.112,0.112,0.106,0.111,0.111,0.109,0.11,0.113,0.11],"error":[],"mean":0.1100794360006735},{"name":"Q13","sql":"SELECT OriginCityName, count(*) AS c FROM default.ontime GROUP BY OriginCityName ORDER BY c DESC LIMIT 10","min":0.105,"max":0.114,"median":0.1085,"std_dev":0.0024269322199023217,"read_row":0,"read_byte":0,"time":[0.108,0.111,0.105,0.108,0.106,0.11,0.114,0.11,0.109,0.108],"error":[],"mean":0.10887310599906294},{"name":"Q14","sql":"SELECT count(*) FROM default.ontime;","min":0.017,"max":0.018,"median":0.018,"std_dev":0.0004898979485566344,"read_row":1,"read_byte":1,"time":[0.018,0.018,0.017,0.018,0.017,0.017,0.018,0.018,0.018,0.017],"error":[],"mean":0.017593128371369084}]}